memgraph_toolbox/__init__.py
memgraph_toolbox/memgraph_toolbox.py
memgraph_toolbox/py.typed
memgraph_toolbox/api/__init__.py
memgraph_toolbox/api/memgraph.py
memgraph_toolbox/api/tool.py
memgraph_toolbox/api/toolbox.py
memgraph_toolbox/client/__init__.py
memgraph_toolbox/client/mcp_prompt.py
memgraph_toolbox/evals/__init__.py
memgraph_toolbox/evals/coherence.py
memgraph_toolbox/tests/__init__.py
memgraph_toolbox/tests/test_embedding.py
memgraph_toolbox/tests/test_eval_coherence.py
memgraph_toolbox/tests/test_mcp_prompt.py
memgraph_toolbox/tests/test_toolbox.py
memgraph_toolbox/tests/test_tools.py
memgraph_toolbox/tools/__init__.py
memgraph_toolbox/tools/betweenness_centrality.py
memgraph_toolbox/tools/config.py
memgraph_toolbox/tools/constraint.py
memgraph_toolbox/tools/cypher.py
memgraph_toolbox/tools/index.py
memgraph_toolbox/tools/node_neighborhood.py
memgraph_toolbox/tools/node_vector_search.py
memgraph_toolbox/tools/page_rank.py
memgraph_toolbox/tools/schema.py
memgraph_toolbox/tools/storage.py
memgraph_toolbox/tools/trigger.py
memgraph_toolbox/utils/embedding.py
memgraph_toolbox/utils/logger.py
memgraph_toolbox/utils/serialization.py
memgraph_toolbox-0.1.6.dist-info/METADATA
memgraph_toolbox-0.1.6.dist-info/WHEEL
memgraph_toolbox-0.1.6.dist-info/licenses/LICENSE
memgraph_toolbox-0.1.6.dist-info/RECORD
