Metadata-Version: 2.4
Name: memgraph-toolbox
Version: 0.1.6
Summary: Memgraph toolbox library for Memgraph AI tools and utilities
Project-URL: Homepage, https://github.com/memgraph/ai-toolkit
Project-URL: Source, https://github.com/memgraph/ai-toolkit
Project-URL: Issues, https://github.com/memgraph/ai-toolkit/issues
Author-email: antejavor <ante.javor@memgraph.io>
License: MIT
License-File: LICENSE
Keywords: ai,graph,memgraph,toolkit
Classifier: Intended Audience :: Developers
Classifier: License :: OSI Approved :: MIT License
Classifier: Programming Language :: Python :: 3
Classifier: Programming Language :: Python :: 3.10
Classifier: Programming Language :: Python :: 3.11
Classifier: Programming Language :: Python :: 3.12
Requires-Python: >=3.10
Requires-Dist: deepeval>=3.5.2
Requires-Dist: litellm>=1.77.1
Requires-Dist: mcp>=1.14.1
Requires-Dist: neo4j>=5.28.1
Requires-Dist: numpy>=2.2.6
Requires-Dist: sentence-transformers>=5.1.0
Requires-Dist: torch>=2.8.0
Provides-Extra: test
Requires-Dist: pytest-asyncio>=0.26.0; extra == 'test'
Requires-Dist: pytest>=8.3.5; extra == 'test'
